amurex/__init__.py
amurex/_version.py
amurex/client.py
amurex/clientconnection.py
amurex/security.py
amurex/channels/__init__.py
amurex/channels/execsession.py
amurex/channels/pflocal.py
amurex/channels/ptysession.py
amurex/channels/sftp.py
amurex/channels/shellsession.py
amurex/common/__init__.py
amurex/common/credential.py
amurex/common/factory.py
amurex/common/knownhosts.py
amurex/common/settings.py
amurex/common/target.py
amurex/crypto/__init__.py
amurex/crypto/mpint.py
amurex/crypto/auth/__init__.py
amurex/crypto/auth/privkey.py
amurex/crypto/compression/__init__.py
amurex/crypto/compression/compzlib.py
amurex/crypto/compression/none.py
amurex/crypto/encryption/__init__.py
amurex/crypto/encryption/aes128ctr.py
amurex/crypto/encryption/aes192ctr.py
amurex/crypto/encryption/aes256ctr.py
amurex/crypto/extras/__init__.py
amurex/crypto/extras/pure25519/__init__.py
amurex/crypto/extras/pure25519/_ed25519.py
amurex/crypto/extras/pure25519/basic.py
amurex/crypto/extras/pure25519/ed25519.py
amurex/crypto/extras/pure25519/eddsa.py
amurex/crypto/kex/__init__.py
amurex/crypto/kex/curve25519.py
amurex/crypto/kex/dh.py
amurex/crypto/kex/dhprimes.py
amurex/crypto/kex/ecdhnist.py
amurex/crypto/kex/nistp256.py
amurex/crypto/kex/nistp384.py
amurex/crypto/kex/nistp521.py
amurex/crypto/keys/__init__.py
amurex/crypto/keys/curve25519.py
amurex/crypto/keys/ecdsa.py
amurex/crypto/keys/rsa.py
amurex/crypto/mac/__init__.py
amurex/crypto/mac/hmacsha1.py
amurex/crypto/mac/hmacsha256.py
amurex/crypto/mac/hmacsha512.py
amurex/examples/__init__.py
amurex/examples/cmdexec.py
amurex/examples/cmdshell.py
amurex/examples/cmdshellpty.py
amurex/examples/cmdshellpty2.py
amurex/examples/connect_user_key.py
amurex/examples/connect_user_pass.py
amurex/examples/connect_user_pass_hosts.py
amurex/examples/conntest3.py
amurex/examples/sftp_download.py
amurex/extras/__init__.py
amurex/extras/pfsocket.py
amurex/extras/socks.py
amurex/protocol/__init__.py
amurex/protocol/messages.py
amurex-0.0.4.dist-info/LICENSE
amurex-0.0.4.dist-info/METADATA
amurex-0.0.4.dist-info/WHEEL
amurex-0.0.4.dist-info/top_level.txt
amurex-0.0.4.dist-info/zip-safe
amurex-0.0.4.dist-info/RECORD
